asterix/__init__.py
asterix/agent.py
asterix/core/__init__.py
asterix/core/config.py
asterix/core/embeddings.py
asterix/core/llm_manager.py
asterix/storage/__init__.py
asterix/storage/agent_state.py
asterix/storage/qdrant_client.py
asterix/tools/__init__.py
asterix/tools/archival.py
asterix/tools/base.py
asterix/tools/conversation.py
asterix/tools/core_memory.py
asterix/utils/__init__.py
asterix/utils/health.py
asterix/utils/tokens.py
asterix_agent-0.1.4.dist-info/licenses/LICENSE
asterix_agent-0.1.4.dist-info/METADATA
asterix_agent-0.1.4.dist-info/WHEEL
asterix_agent-0.1.4.dist-info/top_level.txt
asterix_agent-0.1.4.dist-info/RECORD
