Metadata-Version: 2.4
Name: asterix-agent
Version: 0.1.4
Summary: Stateful AI agents with editable memory blocks and persistent storage
Author-email: Aditya Sarade <aditya.sarade2003@gmail.com>
License: MIT
Project-URL: Homepage, https://github.com/adityasarade/Asterix
Project-URL: Documentation, https://github.com/adityasarade/Asterix#readme
Project-URL: Repository, https://github.com/adityasarade/Asterix
Project-URL: Issues, https://github.com/adityasarade/Asterix/issues
Keywords: ai,agents,memory,llm,qdrant,stateful
Classifier: Development Status :: 4 - Beta
Classifier: Intended Audience :: Developers
Classifier: License :: OSI Approved :: MIT License
Classifier: Programming Language :: Python :: 3
Classifier: Programming Language :: Python :: 3.10
Classifier: Programming Language :: Python :: 3.11
Classifier: Programming Language :: Python :: 3.12
Classifier: Topic :: Software Development :: Libraries :: Python Modules
Classifier: Topic :: Scientific/Engineering :: Artificial Intelligence
Classifier: Operating System :: OS Independent
Classifier: Natural Language :: English
Classifier: Framework :: Pydantic
Classifier: Typing :: Typed
Requires-Python: >=3.10
License-File: LICENSE
Requires-Dist: openai>=1.30.0
Requires-Dist: groq>=0.8.0
Requires-Dist: qdrant-client>=1.7.0
Requires-Dist: sentence-transformers>=2.2.2
Requires-Dist: tiktoken>=0.5.0
Requires-Dist: pyyaml>=6.0.1
Requires-Dist: python-dotenv>=1.0.0
Requires-Dist: pydantic>=2.5.0
Requires-Dist: httpx>=0.25.0
Requires-Dist: numpy>=1.24.0
Provides-Extra: dev
Requires-Dist: pytest>=7.4.0; extra == "dev"
Requires-Dist: pytest-asyncio>=0.21.0; extra == "dev"
Requires-Dist: pytest-cov>=4.1.0; extra == "dev"
Requires-Dist: black>=23.0.0; extra == "dev"
Requires-Dist: isort>=5.12.0; extra == "dev"
Requires-Dist: flake8>=6.0.0; extra == "dev"
Dynamic: license-file
